{
    "word": "video",
    "idx": null,
    "cur_book_name": null,
    "default_phonetic": null,
    "us_phonetic": "[ˈvɪdioʊ]",
    "uk_phonetic": "[ˈvɪdiəʊ]",
    "default_audio_url_dict": {},
    "us_audio_url_dict": {
        "bing": "https://dictionary.blob.core.chinacloudapi.cn/media/audio/tom/0c/21/0C21E3AE5FCF556C434A34D37AD6996A.mp3"
    },
    "uk_audio_url_dict": {
        "bing": "https://dictionary.blob.core.chinacloudapi.cn/media/audio/george/0c/21/0C21E3AE5FCF556C434A34D37AD6996A.mp3"
    },
    "ai_audio_url_dict": {},
    "default_audio_path_dict": {},
    "us_audio_path_dict": {},
    "uk_audio_path_dict": {},
    "ai_audio_path_dict": {},
    "meaning_str": {
        "bing": "n. 视频；录影；录像带；盒式录像带\nv. 录电视节目；给…录像\nadj. 电视(用)的\n网络. 影像；影片；视讯"
    },
    "meaning_dict": {
        "bing": {
            "n.": "视频；录影；录像带；盒式录像带",
            "v.": "录电视节目；给…录像",
            "adj.": "电视(用)的",
            "网络.": "影像；影片；视讯"
        }
    },
    "w_plural": null,
    "w_third": null,
    "w_ing": null,
    "w_done": null,
    "w_past": null,
    "sentence_num": 3,
    "sentence_dict": {
        "bing": {
            "1": {
                "en": "Investigators are now studying surveillance video from the hotel, but have said the footage will not be made public.",
                "cn": "调查人员目前正在研究酒店的监控录像，但已经表示这些画面将不会公开。"
            },
            "2": {
                "en": "Deep sea fishing hunting video game over man's mode of description Model is, up to one mode of fishing is, let me tell you!",
                "cn": "模式是什么，捕鱼达人模式是什么，下面让我来告诉你吧！"
            },
            "3": {
                "en": "Oscar: Nope. Nothing as luxurious as any of those. Just a set of English video cassettes.",
                "cn": "不是，可不是那种豪华的东西。只是一套英语录像带。"
            }
        }
    },
    "sentence_audio_url_dict": {
        "bing": {
            "1": "https://dictionary.blob.core.chinacloudapi.cn/media/audio/tom/0b/e9/0BE9B99A59C6E499B468340D23D3AE65.mp3",
            "2": "https://dictionary.blob.core.chinacloudapi.cn/media/audio/tom/c7/11/C711D95BEB7D6A9BC574F2B02E723818.mp3",
            "3": "https://dictionary.blob.core.chinacloudapi.cn/media/audio/tom/b0/0a/B00A5FB6EC00202BEDE1AEB1009F9675.mp3"
        }
    },
    "sentence_audio_path_dict": {},
    "picture_num": 0,
    "picture_url_dict": {
        "bing": []
    },
    "picture_path_dict": {},
    "level": null,
    "oxford_level": null
}