{
    "route": {
        "name": "text",
        "path": "/text",
        "hash": "",
        "query": {
            "keyword": "efficiency",
            "transfrom": "auto",
            "transto": "zh-CHS",
            "model": "general",
            "errcode": "s10"
        },
        "params": {},
        "fullPath": "/text?keyword=efficiency&transfrom=auto&transto=zh-CHS&model=general&errcode=s10",
        "meta": {
            "mtype": [
                "textTranslate",
                "language",
                "voice"
            ]
        },
        "from": {
            "name": null,
            "path": "/",
            "hash": "",
            "query": {},
            "params": {},
            "fullPath": "/",
            "meta": {}
        }
    },
    "common": {
        "CONFIG": {
            "wuid": 1733664646548,
            "loginInfo": {},
            "isIE": 0,
            "isHitSsrSwitch": true,
            "isHitWritebookSwitch": false,
            "isHitAmsSwitch": true,
            "promotionList": "{\n    \"pc_bottom\":{\n        \"imgsrc\":\"//dlweb.sogoucdn.com/translate/ssr/static/img/banner-side03.2eb72c9.png\",\n        \"qcsrc\":\"//dlweb.sogoucdn.com/translate/ssr/static/img/banner-side03.2eb72c9.png\"\n    },\n    \"pc_middle\":[\n        {\n            \"src\":\"//img03.sogoucdn.com/app/a/200797/03d38a87-552b-4ffe-a4f2-ea0de8ae156c\",\n            \"bgColor\":\"#ffffff\",\n            \"link\":\"\"\n        }\n    ],\n    \"pc_survey\":{\n        \"icon\":\"//img01.sogoucdn.com/app/a/200797/0faf7ee3-d4e7-40e7-9ec7-46ae062aa750\",\n        \"link\":\"https://wj.qq.com/s2/8193148/806d/\"\n    }\n}",
            "bannerData": [],
            "isHitAsideSurvey": false,
            "secretCode": 109984457,
            "uuid": "c019a490-886d-45aa-a912-ea53e13985fc",
            "referer": "",
            "approveToken": "65BBB70115C8A60F05032CC6446FC33D05F60C6367559F86",
            "loadTime": 1733664646550,
            "ua": "Mozilla/5.0 (Windows NT 10.0; Win64; x64) AppleWebKit/537.36 (KHTML, like Gecko) Chrome/130.0.0.0 Safari/537.36 Edg/130.0.0.0",
            "fcp": "159.65.124.238",
            "temporaryId": "",
            "fileId": ""
        },
        "hotWords": [],
        "isFromCollect": false,
        "psdModify": {
            "currentStep": 1,
            "scode": "",
            "username": ""
        },
        "loginStatus": true,
        "feedBackModule": false,
        "showPromotionPopup": {
            "show": false,
            "type": ""
        },
        "showPromotionPCDownload": false,
        "showShareBomb": false,
        "shareData": null,
        "showAppDownLoad": false,
        "showLoginDialog": false,
        "showLoading": {
            "show": false
        },
        "toast": {
            "show": false,
            "text": "",
            "loading": false
        },
        "modelToast": {
            "show": false,
            "text": ""
        },
        "selectionGlobalShow": true,
        "selectionInfo": {
            "left": 0,
            "top": 0,
            "show": false,
            "from": "",
            "to": "",
            "val": "",
            "area": ""
        },
        "showConfirmDialog": false,
        "promotionList": {
            "pc_bottom": {
                "imgsrc": "//dlweb.sogoucdn.com/translate/ssr/static/img/banner-side03.2eb72c9.png",
                "qcsrc": "//dlweb.sogoucdn.com/translate/ssr/static/img/banner-side03.2eb72c9.png"
            },
            "pc_middle": [
                {
                    "src": "//img03.sogoucdn.com/app/a/200797/03d38a87-552b-4ffe-a4f2-ea0de8ae156c",
                    "bgColor": "#ffffff",
                    "link": ""
                }
            ],
            "pc_survey": {
                "icon": "//img01.sogoucdn.com/app/a/200797/0faf7ee3-d4e7-40e7-9ec7-46ae062aa750",
                "link": "https://wj.qq.com/s2/8193148/806d/"
            }
        },
        "transTypeTxt": "text",
        "fixedTabStatus": 0,
        "bodyTop": 0,
        "ifHideUserOperation": false
    },
    "textTranslate": {
        "prevTransQuery": "",
        "translateData": {
            "translate": {
                "zly": "zly",
                "errorCode": "0",
                "qc_type": "1",
                "index": "content0",
                "from": "en",
                "source": "sogou",
                "text": "efficiency",
                "to": "zh-CHS",
                "id": "c019a490-886d-45aa-a912-ea53e13985fc",
                "dit": "效率",
                "orig_text": "efficiency",
                "md5": ""
            },
            "detect": {
                "zly": "zly",
                "detect": "en",
                "errorCode": "0",
                "language": "英语",
                "id": "a1ae0fa0-b568-11ef-8d83-7d4ad7f45f27",
                "text": "efficiency"
            },
            "sgtkn": "65BBB70615C8A60F05032CC6446FC33D05F60C6367559F86",
            "wordCard": {
                "title": "efficiency",
                "show": true,
                "usualDict": [
                    {
                        "values": [
                            "效率；功效；效能；绩效；能效；性能；生产力；实用性；功率；功率比；经济性"
                        ],
                        "pos": "n."
                    }
                ],
                "secondQuery": "",
                "exchange": {
                    "word_pl": [
                        "efficiencies"
                    ]
                },
                "levelList": [
                    "高中",
                    "四级",
                    "六级",
                    "考研",
                    "考博",
                    "托福"
                ]
            },
            "detail": {
                "synonym": [
                    {
                        "word_list": [
                            "virtue",
                            "potency"
                        ],
                        "pos": "n.",
                        "mean": "效率；效能；功效"
                    }
                ],
                "antonym": [
                    {
                        "word_list": [
                            "inefficiency"
                        ],
                        "pos": "",
                        "mean": ""
                    }
                ],
                "affix": {
                    "word": "efficiency",
                    "sub_affix_info_list": [
                        {
                            "affix_sense_info": [
                                {
                                    "sample": [
                                        {
                                            "word": "effect",
                                            "mean": "n. 结果；作用；影响；效果；财产；财物；程度；效力；感受"
                                        },
                                        {
                                            "word": "effort",
                                            "mean": "n. 努力；成果；成就；奋力；勉力；作用力；共同努力"
                                        }
                                    ],
                                    "derivatives": "",
                                    "affix_sense_chinese": "出来, 从...离开, 从...向外",
                                    "affix_type": "prefix"
                                }
                            ],
                            "affix": "ef-",
                            "affix_mean": "出来, 从...向外"
                        },
                        {
                            "affix_sense_info": [
                                {
                                    "sample": [],
                                    "derivatives": "",
                                    "affix_sense_chinese": "做, 制作",
                                    "affix_type": "prefix"
                                }
                            ],
                            "affix": "fic-",
                            "affix_mean": "做, 制作"
                        },
                        {
                            "affix_sense_info": [
                                {
                                    "sample": [
                                        {
                                            "word": "agency",
                                            "mean": "n. 代理；中介；代理处；代办处；作用；机构；办事处；起作用的事物"
                                        },
                                        {
                                            "word": "competency",
                                            "mean": "n. 资格；能力"
                                        },
                                        {
                                            "word": "contingency",
                                            "mean": "n. 可能发生的事件；不确定的事件；偶然性；意外；应急储备；可能性；不测；应急措施；应急开支"
                                        },
                                        {
                                            "word": "currency",
                                            "mean": "n. 通货；货币；通用；流通；通行；流行；流通（或流行）时间"
                                        },
                                        {
                                            "word": "emergency",
                                            "mean": "n. 紧急情况；不测事件；预备队员；替补队员；第二次世界大战；急诊病人；急症病人；紧急情况下出现（或所需、使用）的；急诊室"
                                        },
                                        {
                                            "word": "fluency",
                                            "mean": "n. 流畅；流利；外语说写流利（或流畅）的能力；流畅的表达能力；优美自如"
                                        },
                                        {
                                            "word": "presidency",
                                            "mean": "n. 总统职务；总统任期；圣餐主持"
                                        },
                                        {
                                            "word": "tendency",
                                            "mean": "n. 趋势；趋向；倾向；政治社团"
                                        }
                                    ],
                                    "derivatives": "",
                                    "affix_sense_chinese": "名词后缀, \"性质, 状态, 机构\"",
                                    "affix_type": "suffix"
                                }
                            ],
                            "affix": "-ency",
                            "affix_mean": "性质, 状态"
                        }
                    ],
                    "word_mean": "n. 功效"
                },
                "wordRootInfo": {
                    "word_info_list": [
                        {
                            "word": "efficient",
                            "pos_mean_info_list": [
                                {
                                    "pos": "adj.",
                                    "mean": "有效率的；有能力的；生效的"
                                }
                            ]
                        },
                        {
                            "word": "efficiently",
                            "pos_mean_info_list": [
                                {
                                    "pos": "adv.",
                                    "mean": "有效地；效率高地（efficient的副词形式）"
                                }
                            ]
                        },
                        {
                            "word": "efficacy",
                            "pos_mean_info_list": [
                                {
                                    "pos": "n.",
                                    "mean": "功效，效力"
                                }
                            ]
                        }
                    ],
                    "root_word": "efficient"
                },
                "word_difference_info": [],
                "word_group": [
                    {
                        "brief_definition": "工作效率；办公效率；劳动效率",
                        "phrase": "work efficiency",
                        "pos": ""
                    },
                    {
                        "brief_definition": "提高效率",
                        "phrase": "increase efficiency",
                        "pos": ""
                    },
                    {
                        "brief_definition": "热效率",
                        "phrase": "thermal efficiency",
                        "pos": "n."
                    },
                    {
                        "brief_definition": "容积效率",
                        "phrase": "volumetric efficiency",
                        "pos": "n."
                    },
                    {
                        "brief_definition": "能源效率；能量效率；能效",
                        "phrase": "energy efficiency",
                        "pos": ""
                    },
                    {
                        "brief_definition": "高效率；高效能",
                        "phrase": "high efficiency",
                        "pos": ""
                    },
                    {
                        "brief_definition": "经济效率；经济效益；经济运行效率",
                        "phrase": "economic efficiency",
                        "pos": ""
                    },
                    {
                        "brief_definition": "生产效率；生产的效率",
                        "phrase": "production efficiency",
                        "pos": ""
                    },
                    {
                        "brief_definition": "提高效率",
                        "phrase": "improve efficiency",
                        "pos": ""
                    },
                    {
                        "brief_definition": "运营效率；业务效率；运行效率",
                        "phrase": "operational efficiency",
                        "pos": ""
                    },
                    {
                        "brief_definition": "市场效率；市场的效率；市场效益",
                        "phrase": "market efficiency",
                        "pos": ""
                    },
                    {
                        "brief_definition": "学习效率；学习的效率",
                        "phrase": "learning efficiency",
                        "pos": ""
                    },
                    {
                        "brief_definition": "最大效率；最高效率；最大效能",
                        "phrase": "maximum efficiency",
                        "pos": ""
                    },
                    {
                        "brief_definition": "燃油效率；燃料效率",
                        "phrase": "fuel efficiency",
                        "pos": ""
                    },
                    {
                        "brief_definition": "成本效率；费用效率；成本效益",
                        "phrase": "cost efficiency",
                        "pos": ""
                    },
                    {
                        "brief_definition": "促进效率；提高效率",
                        "phrase": "promote efficiency",
                        "pos": ""
                    },
                    {
                        "brief_definition": "提高效率",
                        "phrase": "raise efficiency",
                        "pos": ""
                    },
                    {
                        "brief_definition": "效率比率；效率比例",
                        "phrase": "efficiency ratio",
                        "pos": ""
                    },
                    {
                        "brief_definition": "伟大的效率；效率高",
                        "phrase": "great efficiency",
                        "pos": ""
                    },
                    {
                        "brief_definition": "配置效率；分配效率；调配效率",
                        "phrase": "allocative efficiency",
                        "pos": ""
                    }
                ],
                "bilingual": [
                    {
                        "source": "His work <em>efficiency</em> is always high.",
                        "target": "他的工作效率总是很高。",
                        "url": ""
                    },
                    {
                        "source": "This machine has very high <em>efficiency</em>.",
                        "target": "这台机器的效率非常高。",
                        "url": ""
                    },
                    {
                        "source": "The reform aims to improve <em>efficiency</em>.",
                        "target": "这项改革旨在提高效率。",
                        "url": ""
                    },
                    {
                        "source": "We need to improve our work <em>efficiency</em>.",
                        "target": "我们需要提高工作效率。",
                        "url": ""
                    },
                    {
                        "source": "Teamwork can improve work <em>efficiency</em>.",
                        "target": "团队协作能提高工作效率。",
                        "url": ""
                    },
                    {
                        "source": "Saving time means higher <em>efficiency</em>.",
                        "target": "节约时间意味着更高的效率。",
                        "url": ""
                    },
                    {
                        "source": "We need to improve production <em>efficiency</em>.",
                        "target": "我们需要提高生产效率。",
                        "url": ""
                    },
                    {
                        "source": "We need to increase production <em>efficiency</em>.",
                        "target": "我们需要增益生产效率。",
                        "url": ""
                    },
                    {
                        "source": "The prius has excellent fuel <em>efficiency</em>.",
                        "target": "普锐斯的燃油效率非常高。",
                        "url": ""
                    },
                    {
                        "source": "This machine operates with high <em>efficiency</em>.",
                        "target": "这台机器以高效率运行。",
                        "url": ""
                    }
                ]
            },
            "book": {
                "yingyinNormal": [
                    {
                        "picUrl": "http://pic03.sogoucdn.com/s3/a/201051/368277e4523e7b27b12887e16057df56_64015.jpg",
                        "audioUrl": "http://pic02.sogoucdn.com/s3/a/201051/6c3070b38a486651cbae83f7691c78e2_43960.mp3",
                        "isLavafox": true,
                        "en": "Come here, boy. Turn the other cheek. See, what our newer designs gained in <em>efficiency</em>, they lost in grace.",
                        "zh": "到这来，孩子，露出另一张脸，我们的新设计在效率方面大为提高，却失去了优雅。",
                        "videoNameZh": "《西部世界 第一季》",
                        "videoNameEn": "《Westworld Season 1》",
                        "url": "http://bisentence_movie.sogou.com/8a00063700f3f24082c5b316bacb6637_dbe9f2872824b16589bfdca08a0d0b1a56c25f37"
                    },
                    {
                        "picUrl": "http://pic02.sogoucdn.com/s3/a/201051/84db3d779d7851ae88ef308619fcf09a_6035.jpg",
                        "audioUrl": "http://pic02.sogoucdn.com/s3/a/201051/4c22be12b62d165b011400bdcd52c6b5_60371.mp3",
                        "isLavafox": true,
                        "en": "But to us, it's all about trying to identify and cut out as much waste as you can to lower your costs and improve the <em>efficiency</em> and the speed by which you do your work.",
                        "zh": "但是对于我们来说，都是在识别以及去掉尽可能多的浪费来降低成本和提高效率和你工作的速度。",
                        "videoNameZh": "《透视美国》",
                        "videoNameEn": "《America Revealed》",
                        "url": "http://bisentence_movie.sogou.com/5971a55d5beaec81f29e7669b164f1d8_9bc21295212bee4a35f1fcfb55797d463344cac1"
                    }
                ]
            },
            "pic": "",
            "voice": {
                "phonetic": [
                    {
                        "text": "ɪˈfɪʃnsi",
                        "type": "uk",
                        "filename": "http://dlweb.sogoucdn.com/phonetic/sogouvoices/570_efficiency_uk.mp3"
                    },
                    {
                        "text": "ɪˈfɪʃnsi",
                        "type": "usa",
                        "filename": "http://dlweb.sogoucdn.com/phonetic/sogouvoices/570_efficiency_usa.mp3"
                    }
                ]
            },
            "dictType": "oxford_buchong",
            "kaoyan": {
                "exam_freq_info": [
                    {
                        "sense_tier": 10,
                        "pos": "n",
                        "chinese": "效率",
                        "sense_tier_ratio": 100
                    },
                    {
                        "sense_tier": 0,
                        "pos": "n",
                        "chinese": "功率",
                        "sense_tier_ratio": 0
                    }
                ],
                "word": "efficiency",
                "word_level_phrase_info": [
                    {
                        "brief_definition": "工作效率；办公效率；劳动效率",
                        "phrase": "work efficiency",
                        "pos": "phr"
                    }
                ],
                "direction_info": {
                    "ranges": 12,
                    "description": "数据源自2012-2023年12年间全国考研试卷，由搜狗翻译进行大数据分析汇总，数据仅供参考。\n\n<highlight> 考频分布</highlight>\n由搜狗翻译收集历年真题试卷、汇总单词出现的总频次、释义分布。题型选自2012-2023年全国考研英语一和考研英语二共24套考研试卷，包括阅读、完型填空、翻译、写作等所有题型。\n\n<highlight> 考纲释义</highlight>\n精选全国考研考纲词汇、单词义项，由搜狗大数据与考纲、历年真题进行匹配。\n\n<highlight>真题例句</highlight>\n精选2012-2023年12年间全国考研英语一和考研英语二试卷，由搜狗大数据与搜索内容匹配历年真题例句。\n\n搜狗翻译拥有最终解释权。"
                },
                "important_score": 2,
                "word_family": {
                    "derivative_info_list": [
                        {
                            "derivative_info_list": [
                                {
                                    "derivative_info_list": [],
                                    "word": "efficiently",
                                    "mean": "adv. 有效地；效率高地"
                                },
                                {
                                    "derivative_info_list": [],
                                    "word": "efficiency",
                                    "mean": "n. 功效；效力；效能；效力的提高；效率"
                                }
                            ],
                            "word": "efficient",
                            "mean": "adj. 效率高的；有能力的；能胜任的；防止造成…的浪费的"
                        }
                    ],
                    "word": "efficacy",
                    "mean": "n. 功效；效力；效能"
                },
                "total_exam_freq": 10,
                "sense": {
                    "sense_num": 2,
                    "sense_info_list": [
                        {
                            "en": "skillfulness in avoiding wasted time and effort",
                            "zh": "效率",
                            "pos": "n",
                            "synonyms": "",
                            "antonyms": "",
                            "examination_example": [
                                {
                                    "sentence": "The declining <highlight>efficiency</highlight> of the TSA.",
                                    "month": -1,
                                    "source": "英语一",
                                    "coll": "",
                                    "sentence_trans": "TSA（美国联邦运输安全管理局）不断下降的效率。",
                                    "year": 2017,
                                    "type": "阅读理解A",
                                    "day": -1
                                },
                                {
                                    "sentence": "You'd think this might fuel the <highlight>efficiency</highlight> mind-set, but in fact, Eberle notes, such ritualistic behaviour helps us \"step outside time's flow\" into \"soul time.\"",
                                    "month": -1,
                                    "source": "英语二",
                                    "coll": "",
                                    "sentence_trans": "你也许认为这会助长效率思维定势，但事实上，埃伯利指出，这种惯常的行为有助于我们“走出时间的流逝”，并进入“心灵时间”。",
                                    "year": 2016,
                                    "type": "阅读理解A",
                                    "day": -1
                                },
                                {
                                    "sentence": "The words that have mattered are <highlight>efficiency</highlight>, flexibility, shareholder value, business-friendly, wealth generation, sales, impact and, in newspapers, circulation.",
                                    "month": -1,
                                    "source": "英语一",
                                    "coll": "",
                                    "sentence_trans": "真正重要的词是效率、灵活性、股东价值、商业友好、创造财富、销售量、影响力和报纸的发行量。",
                                    "year": 2015,
                                    "type": "阅读理解A",
                                    "day": -1
                                }
                            ]
                        },
                        {
                            "synonyms": "",
                            "en": "the ratio of the output to the input of any system",
                            "zh": "功率",
                            "pos": "n",
                            "antonyms": ""
                        }
                    ]
                },
                "word_affix": {
                    "word": "efficiency",
                    "sub_affix_info_list": [
                        {
                            "affix_sense_info": [
                                {
                                    "sample": [
                                        {
                                            "word": "effect",
                                            "mean": "n. 结果；作用；影响；效果；财产；财物；程度；效力；感受"
                                        },
                                        {
                                            "word": "effort",
                                            "mean": "n. 努力；成果；成就；奋力；勉力；作用力；共同努力"
                                        }
                                    ],
                                    "derivatives": "",
                                    "affix_sense_chinese": "出来, 从...离开, 从...向外",
                                    "affix_type": "prefix"
                                }
                            ],
                            "affix": "ef-",
                            "affix_mean": "出来, 从...向外"
                        },
                        {
                            "affix_sense_info": [
                                {
                                    "sample": [],
                                    "derivatives": "",
                                    "affix_sense_chinese": "做, 制作",
                                    "affix_type": "prefix"
                                }
                            ],
                            "affix": "fic-",
                            "affix_mean": "做, 制作"
                        },
                        {
                            "affix_sense_info": [
                                {
                                    "sample": [
                                        {
                                            "word": "agency",
                                            "mean": "n. 代理；中介；代理处；代办处；作用；机构；办事处；起作用的事物"
                                        },
                                        {
                                            "word": "competency",
                                            "mean": "n. 资格；能力"
                                        },
                                        {
                                            "word": "contingency",
                                            "mean": "n. 可能发生的事件；不确定的事件；偶然性；意外；应急储备；可能性；不测；应急措施；应急开支"
                                        },
                                        {
                                            "word": "currency",
                                            "mean": "n. 通货；货币；通用；流通；通行；流行；流通（或流行）时间"
                                        },
                                        {
                                            "word": "emergency",
                                            "mean": "n. 紧急情况；不测事件；预备队员；替补队员；第二次世界大战；急诊病人；急症病人；紧急情况下出现（或所需、使用）的；急诊室"
                                        },
                                        {
                                            "word": "fluency",
                                            "mean": "n. 流畅；流利；外语说写流利（或流畅）的能力；流畅的表达能力；优美自如"
                                        },
                                        {
                                            "word": "presidency",
                                            "mean": "n. 总统职务；总统任期；圣餐主持"
                                        },
                                        {
                                            "word": "tendency",
                                            "mean": "n. 趋势；趋向；倾向；政治社团"
                                        }
                                    ],
                                    "derivatives": "",
                                    "affix_sense_chinese": "名词后缀, \"性质, 状态, 机构\"",
                                    "affix_type": "suffix"
                                }
                            ],
                            "affix": "-ency",
                            "affix_mean": "性质, 状态"
                        }
                    ],
                    "word_mean": "n. 功效"
                }
            },
            "CET6": {
                "exam_freq_info": [
                    {
                        "sense_tier": 15,
                        "pos": "n",
                        "chinese": "效率",
                        "sense_tier_ratio": 100
                    }
                ],
                "word": "efficiency",
                "direction_info": {
                    "ranges": 8,
                    "description": "数据源自2016.6-2023.6年8年间全六级试卷，由搜狗翻译进行大数据分析汇总，数据仅供参考。\n\n<highlight>考纲释义</highlight>\n精选实考、考纲词汇、单词义项，由搜狗大数据与考纲、历年真题进行匹配。\n\n<highlight>考频分布</highlight>\n由搜狗翻译收集历年真题试卷、汇总单词出现的总频次、释义分布。题型选自2016-2023年51套试卷，包括阅读、听力、翻译等所有题型。\n\n<highlight>真题例句</highlight>\n精选2016-2023年8年间全六级试卷，由搜狗大数据与搜索内容匹配历年真题例句。\n\n搜狗翻译拥有最终解释权。"
                },
                "important_score": 3,
                "word_family": {
                    "derivative_info_list": [
                        {
                            "derivative_info_list": [],
                            "word": "efficiently",
                            "mean": "adv. 有效地；效率高地"
                        },
                        {
                            "derivative_info_list": [],
                            "word": "inefficient",
                            "mean": "adj. 效率差的；效率低的；无效率的"
                        },
                        {
                            "derivative_info_list": [],
                            "word": "efficiency",
                            "mean": "n. 功效；效力；效能；效力的提高；效率"
                        }
                    ],
                    "word": "efficient",
                    "mean": "adj. 效率高的；有能力的；能胜任的；防止造成…的浪费的"
                },
                "total_exam_freq": 15,
                "sense": {
                    "sense_num": 1,
                    "sense_info_list": [
                        {
                            "en": "skillfulness in avoiding wasted time and effort",
                            "zh": "效率",
                            "pos": "n",
                            "synonyms": "productivity,effectiveness",
                            "antonyms": "",
                            "examination_example": [
                                {
                                    "sentence": "It eventually led to less <highlight>efficiency</highlight>.",
                                    "month": 12,
                                    "source": "CET6",
                                    "coll": "",
                                    "sentence_trans": "最终导致效率降低。",
                                    "year": 2021,
                                    "type": "阅读理解C",
                                    "day": -1
                                },
                                {
                                    "sentence": "Promote <highlight>efficiency</highlight> and increase food variety.",
                                    "month": 12,
                                    "source": "CET6",
                                    "coll": "",
                                    "sentence_trans": "提高效率，并增加食物多样性。",
                                    "year": 2021,
                                    "type": "阅读理解C",
                                    "day": -1
                                },
                                {
                                    "sentence": "I don't miss having managers who deliver blunt, harsh feedback in the name of <highlight>efficiency</highlight>.",
                                    "month": 6,
                                    "source": "CET6",
                                    "coll": "",
                                    "sentence_trans": "我不怀念那些以效率为名提供生硬、苛刻反馈的经理。",
                                    "year": 2021,
                                    "type": "听力",
                                    "day": -1
                                }
                            ]
                        }
                    ]
                },
                "word_affix": {
                    "word": "efficiency",
                    "sub_affix_info_list": [
                        {
                            "affix_sense_info": [
                                {
                                    "sample": [
                                        {
                                            "word": "effect",
                                            "mean": "n. 结果；作用；影响；效果；财产；财物；程度；效力；感受"
                                        },
                                        {
                                            "word": "effort",
                                            "mean": "n. 努力；成果；成就；奋力；勉力；作用力；共同努力"
                                        }
                                    ],
                                    "derivatives": "",
                                    "affix_sense_chinese": "出来, 从...离开, 从...向外",
                                    "affix_type": "prefix"
                                }
                            ],
                            "affix": "ef-",
                            "affix_mean": "出来, 从...向外"
                        },
                        {
                            "affix_sense_info": [
                                {
                                    "sample": [],
                                    "derivatives": "",
                                    "affix_sense_chinese": "做, 制作",
                                    "affix_type": "prefix"
                                }
                            ],
                            "affix": "fic-",
                            "affix_mean": "做, 制作"
                        },
                        {
                            "affix_sense_info": [
                                {
                                    "sample": [
                                        {
                                            "word": "agency",
                                            "mean": "n. 代理；中介；代理处；代办处；作用；机构；办事处；起作用的事物"
                                        },
                                        {
                                            "word": "competency",
                                            "mean": "n. 资格；能力"
                                        },
                                        {
                                            "word": "contingency",
                                            "mean": "n. 可能发生的事件；不确定的事件；偶然性；意外；应急储备；可能性；不测；应急措施；应急开支"
                                        },
                                        {
                                            "word": "currency",
                                            "mean": "n. 通货；货币；通用；流通；通行；流行；流通（或流行）时间"
                                        },
                                        {
                                            "word": "emergency",
                                            "mean": "n. 紧急情况；不测事件；预备队员；替补队员；第二次世界大战；急诊病人；急症病人；紧急情况下出现（或所需、使用）的；急诊室"
                                        },
                                        {
                                            "word": "fluency",
                                            "mean": "n. 流畅；流利；外语说写流利（或流畅）的能力；流畅的表达能力；优美自如"
                                        },
                                        {
                                            "word": "presidency",
                                            "mean": "n. 总统职务；总统任期；圣餐主持"
                                        },
                                        {
                                            "word": "tendency",
                                            "mean": "n. 趋势；趋向；倾向；政治社团"
                                        }
                                    ],
                                    "derivatives": "",
                                    "affix_sense_chinese": "名词后缀, \"性质, 状态, 机构\"",
                                    "affix_type": "suffix"
                                }
                            ],
                            "affix": "-ency",
                            "affix_mean": "性质, 状态"
                        }
                    ],
                    "word_mean": "n. 功效"
                },
                "exchange_info": {
                    "word_pl": [
                        "efficiencies"
                    ]
                }
            },
            "CET4": {
                "exam_freq_info": [
                    {
                        "sense_tier": 10,
                        "pos": "n",
                        "chinese": "效率",
                        "sense_tier_ratio": 76.92
                    },
                    {
                        "sense_tier": 2,
                        "pos": "n",
                        "chinese": "(~s)提高功效的方法",
                        "sense_tier_ratio": 15.38
                    },
                    {
                        "sense_tier": 1,
                        "pos": "n",
                        "chinese": "功率",
                        "sense_tier_ratio": 7.69
                    }
                ],
                "word": "efficiency",
                "word_level_phrase_info": [
                    {
                        "brief_definition": "工作效率；办公效率；劳动效率",
                        "phrase": "work efficiency",
                        "pos": "n"
                    }
                ],
                "direction_info": {
                    "ranges": 8,
                    "description": "数据源自2016.6-2023.6年8年间全四级试卷，由搜狗翻译进行大数据分析汇总，数据仅供参考。\n\n<highlight>考纲释义</highlight>\n精选实考、考纲词汇、单词义项，由搜狗大数据与考纲、历年真题进行匹配。\n\n<highlight>考频分布</highlight>\n由搜狗翻译收集历年真题试卷、汇总单词出现的总频次、释义分布。题型选自2016-2023年51套试卷，包括阅读、听力、翻译等所有题型。\n\n<highlight>真题例句</highlight>\n精选2016-2023年8年间试卷，由搜狗大数据与搜索内容匹配历年真题例句。\n\n搜狗翻译拥有最终解释权。"
                },
                "important_score": 3,
                "word_family": {
                    "derivative_info_list": [
                        {
                            "derivative_info_list": [],
                            "word": "efficiently",
                            "mean": "adv. 有效地；效率高地"
                        },
                        {
                            "derivative_info_list": [
                                {
                                    "derivative_info_list": [],
                                    "word": "inefficiently",
                                    "mean": "adv. 无效率地；缺乏能力地"
                                }
                            ],
                            "word": "inefficient",
                            "mean": "adj. 效率差的；效率低的；无效率的"
                        },
                        {
                            "derivative_info_list": [],
                            "word": "efficiency",
                            "mean": "n. 功效；效力；效能；效力的提高；效率"
                        }
                    ],
                    "word": "efficient",
                    "mean": "adj. 效率高的；有能力的；能胜任的；防止造成…的浪费的"
                },
                "total_exam_freq": 13,
                "sense": {
                    "sense_num": 3,
                    "sense_info_list": [
                        {
                            "en": "skillfulness in avoiding wasted time and effort",
                            "zh": "效率",
                            "pos": "n",
                            "synonyms": "",
                            "antonyms": "",
                            "examination_example": [
                                {
                                    "sentence": "There is a big boost in employees' work <highlight>efficiency</highlight>.",
                                    "month": 6,
                                    "source": "CET4",
                                    "coll": "",
                                    "sentence_trans": "员工的工作效率大大提高了。",
                                    "year": 2021,
                                    "type": "阅读理解C",
                                    "day": -1
                                },
                                {
                                    "sentence": "They partner with technology companies to enhance teaching <highlight>efficiency</highlight>.",
                                    "month": 6,
                                    "source": "CET4",
                                    "coll": "",
                                    "sentence_trans": "他们与科技公司合作以提高教学效率。",
                                    "year": 2021,
                                    "type": "阅读理解C",
                                    "day": -1
                                },
                                {
                                    "sentence": "It can improve shopping <highlight>efficiency</highlight>.",
                                    "month": 9,
                                    "source": "CET4",
                                    "coll": "",
                                    "sentence_trans": "它可以提高购物效率。",
                                    "year": 2020,
                                    "type": "听力",
                                    "day": -1
                                }
                            ]
                        },
                        {
                            "en": "ways of wasting less time and money or of saving time or money",
                            "zh": "(~s)提高功效的方法",
                            "pos": "n",
                            "synonyms": "",
                            "antonyms": "",
                            "examination_example": [
                                {
                                    "sentence": "Draw up a list of the <highlight>efficiencies</highlight> to be promised.",
                                    "month": 6,
                                    "source": "CET4",
                                    "coll": "",
                                    "sentence_trans": "拟定一份承诺的效率清单。",
                                    "year": 2021,
                                    "type": "阅读理解C",
                                    "day": -1
                                },
                                {
                                    "sentence": "Swollen expectations have been popped and a long list of promised <highlight>efficiencies</highlight> have been reversed.",
                                    "month": 6,
                                    "source": "CET4",
                                    "coll": "",
                                    "sentence_trans": "膨胀的期望已经破灭，一长串承诺的提高功效的方法已经被逆转。",
                                    "year": 2021,
                                    "type": "阅读理解C",
                                    "day": -1
                                }
                            ]
                        },
                        {
                            "synonyms": "",
                            "en": "the ratio of the output to the input of any system",
                            "zh": "功率",
                            "pos": "n",
                            "antonyms": ""
                        }
                    ]
                },
                "word_affix": {
                    "word": "efficiency",
                    "sub_affix_info_list": [
                        {
                            "affix_sense_info": [
                                {
                                    "sample": [
                                        {
                                            "word": "effect",
                                            "mean": "n. 结果；作用；影响；效果；财产；财物；程度；效力；感受"
                                        },
                                        {
                                            "word": "effort",
                                            "mean": "n. 努力；成果；成就；奋力；勉力；作用力；共同努力"
                                        }
                                    ],
                                    "derivatives": "",
                                    "affix_sense_chinese": "出来, 从...离开, 从...向外",
                                    "affix_type": "prefix"
                                }
                            ],
                            "affix": "ef-",
                            "affix_mean": "出来, 从...向外"
                        },
                        {
                            "affix_sense_info": [
                                {
                                    "sample": [],
                                    "derivatives": "",
                                    "affix_sense_chinese": "做, 制作",
                                    "affix_type": "prefix"
                                }
                            ],
                            "affix": "fic-",
                            "affix_mean": "做, 制作"
                        },
                        {
                            "affix_sense_info": [
                                {
                                    "sample": [
                                        {
                                            "word": "agency",
                                            "mean": "n. 代理；中介；代理处；代办处；作用；机构；办事处；起作用的事物"
                                        },
                                        {
                                            "word": "competency",
                                            "mean": "n. 资格；能力"
                                        },
                                        {
                                            "word": "contingency",
                                            "mean": "n. 可能发生的事件；不确定的事件；偶然性；意外；应急储备；可能性；不测；应急措施；应急开支"
                                        },
                                        {
                                            "word": "currency",
                                            "mean": "n. 通货；货币；通用；流通；通行；流行；流通（或流行）时间"
                                        },
                                        {
                                            "word": "emergency",
                                            "mean": "n. 紧急情况；不测事件；预备队员；替补队员；第二次世界大战；急诊病人；急症病人；紧急情况下出现（或所需、使用）的；急诊室"
                                        },
                                        {
                                            "word": "fluency",
                                            "mean": "n. 流畅；流利；外语说写流利（或流畅）的能力；流畅的表达能力；优美自如"
                                        },
                                        {
                                            "word": "presidency",
                                            "mean": "n. 总统职务；总统任期；圣餐主持"
                                        },
                                        {
                                            "word": "tendency",
                                            "mean": "n. 趋势；趋向；倾向；政治社团"
                                        }
                                    ],
                                    "derivatives": "",
                                    "affix_sense_chinese": "名词后缀, \"性质, 状态, 机构\"",
                                    "affix_type": "suffix"
                                }
                            ],
                            "affix": "-ency",
                            "affix_mean": "性质, 状态"
                        }
                    ],
                    "word_mean": "n. 功效"
                },
                "exchange_info": {
                    "word_pl": [
                        "efficiencies"
                    ]
                }
            },
            "gaokao": {
                "exam_freq_info": [
                    {
                        "sense_tier": 2,
                        "pos": "n",
                        "chinese": "效率; 功效; 效能",
                        "sense_tier_ratio": 100
                    }
                ],
                "word": "efficiency",
                "direction_info": {
                    "ranges": 8,
                    "description": "数据源自2015-2022年8年间全国卷和自主命题省市高考卷，由搜狗翻译进行大数据分析汇总，数据仅供参考。\n\n<highlight> 考频分布</highlight>\n由搜狗翻译收集历年真题试卷、汇总单词出现的总频次、释义分布。题型选自2015-2022年全国卷高考试卷，包括阅读、完形、单选、填空、听力、改错、写作等所有题型。\n\n<highlight> 考纲释义</highlight>\n精选各省市考纲词汇、单词义项，由搜狗大数据与考纲、历年真题进行匹配。\n\n<highlight>真题例句</highlight>\n精选2015-2022年8年间全国卷和自主命题省市高考卷，由搜狗大数据与搜索内容匹配历年真题例句。\n\n搜狗翻译拥有最终解释权。"
                },
                "important_score": 1,
                "word_family": {
                    "derivative_info_list": [
                        {
                            "derivative_info_list": [],
                            "word": "efficiency",
                            "mean": "n. 功效；效力；效能；效力的提高；效率"
                        }
                    ],
                    "word": "efficient",
                    "mean": "adj. 效率高的；有能力的；能胜任的；防止造成…的浪费的"
                },
                "total_exam_freq": 2,
                "sense": {
                    "sense_num": 1,
                    "sense_info_list": [
                        {
                            "en": "",
                            "zh": "效率; 功效; 效能",
                            "pos": "n",
                            "synonyms": "",
                            "antonyms": "",
                            "examination_example": [
                                {
                                    "sentence": "The fear of falling behind in <highlight>efficiency</highlight>.",
                                    "month": -1,
                                    "source": "天津卷",
                                    "coll": "",
                                    "sentence_trans": "担心在效率上落后。",
                                    "year": 2021,
                                    "type": "阅读理解",
                                    "day": -1
                                },
                                {
                                    "sentence": "In France, quality of life is much more important than <highlight>efficiency</highlight> (效率).",
                                    "month": -1,
                                    "source": "新高考Ⅰ卷",
                                    "coll": "",
                                    "sentence_trans": "在法国，生活质量比效率重要得多。",
                                    "year": 2021,
                                    "type": "任务型阅读",
                                    "day": -1
                                }
                            ]
                        }
                    ]
                },
                "word_affix": {
                    "word": "efficiency",
                    "sub_affix_info_list": [
                        {
                            "affix_sense_info": [
                                {
                                    "sample": [
                                        {
                                            "word": "effect",
                                            "mean": "n. 结果；作用；影响；效果；财产；财物；程度；效力；感受"
                                        },
                                        {
                                            "word": "effort",
                                            "mean": "n. 努力；成果；成就；奋力；勉力；作用力；共同努力"
                                        }
                                    ],
                                    "derivatives": "",
                                    "affix_sense_chinese": "出来, 从...离开, 从...向外",
                                    "affix_type": "prefix"
                                }
                            ],
                            "affix": "ef-",
                            "affix_mean": "出来, 从...向外"
                        },
                        {
                            "affix_sense_info": [
                                {
                                    "sample": [],
                                    "derivatives": "",
                                    "affix_sense_chinese": "做, 制作",
                                    "affix_type": "prefix"
                                }
                            ],
                            "affix": "fic-",
                            "affix_mean": "做, 制作"
                        },
                        {
                            "affix_sense_info": [
                                {
                                    "sample": [
                                        {
                                            "word": "agency",
                                            "mean": "n. 代理；中介；代理处；代办处；作用；机构；办事处；起作用的事物"
                                        },
                                        {
                                            "word": "competency",
                                            "mean": "n. 资格；能力"
                                        },
                                        {
                                            "word": "contingency",
                                            "mean": "n. 可能发生的事件；不确定的事件；偶然性；意外；应急储备；可能性；不测；应急措施；应急开支"
                                        },
                                        {
                                            "word": "currency",
                                            "mean": "n. 通货；货币；通用；流通；通行；流行；流通（或流行）时间"
                                        },
                                        {
                                            "word": "emergency",
                                            "mean": "n. 紧急情况；不测事件；预备队员；替补队员；第二次世界大战；急诊病人；急症病人；紧急情况下出现（或所需、使用）的；急诊室"
                                        },
                                        {
                                            "word": "fluency",
                                            "mean": "n. 流畅；流利；外语说写流利（或流畅）的能力；流畅的表达能力；优美自如"
                                        },
                                        {
                                            "word": "presidency",
                                            "mean": "n. 总统职务；总统任期；圣餐主持"
                                        },
                                        {
                                            "word": "tendency",
                                            "mean": "n. 趋势；趋向；倾向；政治社团"
                                        }
                                    ],
                                    "derivatives": "",
                                    "affix_sense_chinese": "名词后缀, \"性质, 状态, 机构\"",
                                    "affix_type": "suffix"
                                }
                            ],
                            "affix": "-ency",
                            "affix_mean": "性质, 状态"
                        }
                    ],
                    "word_mean": "n. 功效"
                }
            },
            "zhongkao": {
                "exam_freq_info": [
                    {
                        "sense_tier": 3,
                        "pos": "n",
                        "chinese": "效率; 功效; 效能",
                        "sense_tier_ratio": 100
                    }
                ],
                "word": "efficiency",
                "total_exam_freq": 3,
                "direction_info": {
                    "ranges": 4,
                    "description": "数据源自2018-2021年4年间全国各省市中考试卷，由搜狗翻译进行大数据分析汇总，数据仅供参考。\n\n<highlight> 考频分布</highlight>\n由搜狗翻译收集历年真题试卷、汇总单词出现的总频次、释义分布。题型选自2018-2021年全国重点省市中考试卷，包括听力、阅读、完形、单选、填空、改错、写作等所有题型。\n\n<highlight> 考纲释义</highlight>\n精选各省市考纲词汇、单词义项，由搜狗大数据与考纲、历年真题进行匹配。\n\n<highlight>真题例句</highlight>\n精选2018-2021年4年间全国各省市中考试卷，由搜狗大数据与搜索内容匹配历年真题例句。\n\n搜狗翻译拥有最终解释权。"
                },
                "important_score": 1,
                "word_family": {
                    "derivative_info_list": [
                        {
                            "derivative_info_list": [
                                {
                                    "derivative_info_list": [],
                                    "word": "efficiently",
                                    "mean": "adv. 有效地；效率高地"
                                },
                                {
                                    "derivative_info_list": [],
                                    "word": "efficiency",
                                    "mean": "n. 功效；效力；效能；效力的提高；效率"
                                }
                            ],
                            "word": "efficient",
                            "mean": "adj. 效率高的；有能力的；能胜任的；防止造成…的浪费的"
                        }
                    ],
                    "word": "efficacy",
                    "mean": "n. 功效；效力；效能"
                },
                "word_level_phrase_info": [
                    {
                        "brief_definition": "提高效率",
                        "phrase": "increase efficiency",
                        "pos": ""
                    }
                ],
                "sense": {
                    "sense_num": 1,
                    "sense_info_list": [
                        {
                            "en": "",
                            "zh": "效率; 功效; 效能",
                            "pos": "n",
                            "synonyms": "",
                            "antonyms": "",
                            "examination_example": [
                                {
                                    "sentence": "E-tickets save time and improve travel <highlight>efficiency</highlight> (效率).",
                                    "month": -1,
                                    "source": "绥化市卷",
                                    "coll": "",
                                    "sentence_trans": "电子机票能节省时间，提高出行效率。",
                                    "year": 2021,
                                    "type": "回答问题",
                                    "day": -1
                                },
                                {
                                    "sentence": "They can save time and improve travel <highlight>efficiency</highlight>.",
                                    "month": -1,
                                    "source": "绥化市卷",
                                    "coll": "",
                                    "sentence_trans": "它们可以节省时间，提高旅行效率。",
                                    "year": 2021,
                                    "type": "回答问题",
                                    "day": -1
                                },
                                {
                                    "sentence": "He says the software has increased <highlight>efficiency</highlight>(效率)， reduced costs and improved relations with patients.",
                                    "month": -1,
                                    "source": "呼和浩特卷",
                                    "coll": "",
                                    "sentence_trans": "他说，该软件提高了效率，降低了成本，改善了与患者的关系。",
                                    "year": 2019,
                                    "type": "阅读理解",
                                    "day": -1
                                }
                            ]
                        }
                    ]
                },
                "word_affix": {
                    "sub_affix_info_list": [
                        {
                            "affix_sense_info": [
                                {
                                    "sample": [
                                        {
                                            "word": "effect",
                                            "mean": "n. 结果；作用；影响；效果；财产；财物；程度；效力；感受"
                                        },
                                        {
                                            "word": "effort",
                                            "mean": "n. 努力；成果；成就；奋力；勉力；作用力；共同努力"
                                        }
                                    ],
                                    "derivatives": "",
                                    "affix_sense_chinese": "出来, 从...离开, 从...向外",
                                    "affix_type": "prefix"
                                }
                            ],
                            "affix": "ef-",
                            "affix_mean": "出来, 从...向外"
                        },
                        {
                            "affix_sense_info": [
                                {
                                    "sample": [],
                                    "derivatives": "",
                                    "affix_sense_chinese": "做, 制作",
                                    "affix_type": "prefix"
                                }
                            ],
                            "affix": "fic-",
                            "affix_mean": "做, 制作"
                        },
                        {
                            "affix_sense_info": [
                                {
                                    "sample": [
                                        {
                                            "word": "agency",
                                            "mean": "n. 代理；中介；代理处；代办处；作用；机构；办事处；起作用的事物"
                                        },
                                        {
                                            "word": "competency",
                                            "mean": "n. 资格；能力"
                                        },
                                        {
                                            "word": "contingency",
                                            "mean": "n. 可能发生的事件；不确定的事件；偶然性；意外；应急储备；可能性；不测；应急措施；应急开支"
                                        },
                                        {
                                            "word": "currency",
                                            "mean": "n. 通货；货币；通用；流通；通行；流行；流通（或流行）时间"
                                        },
                                        {
                                            "word": "emergency",
                                            "mean": "n. 紧急情况；不测事件；预备队员；替补队员；第二次世界大战；急诊病人；急症病人；紧急情况下出现（或所需、使用）的；急诊室"
                                        },
                                        {
                                            "word": "fluency",
                                            "mean": "n. 流畅；流利；外语说写流利（或流畅）的能力；流畅的表达能力；优美自如"
                                        },
                                        {
                                            "word": "presidency",
                                            "mean": "n. 总统职务；总统任期；圣餐主持"
                                        },
                                        {
                                            "word": "tendency",
                                            "mean": "n. 趋势；趋向；倾向；政治社团"
                                        }
                                    ],
                                    "derivatives": "",
                                    "affix_sense_chinese": "名词后缀, \"性质, 状态, 机构\"",
                                    "affix_type": "suffix"
                                }
                            ],
                            "affix": "-ency",
                            "affix_mean": "性质, 状态"
                        }
                    ],
                    "word": "efficiency",
                    "word_mean": "n. 功效"
                }
            },
            "sentencesData": {
                "status": 1,
                "info": "notZh2En",
                "data": {}
            },
            "isAutoMatch": false,
            "Zh2En": false
        },
        "query": "efficiency",
        "result": "效率",
        "tabSelect": "detail",
        "dictionaryType": "oxford_buchong",
        "notFound_show": false,
        "phoneticShow": "",
        "globalShowTranslateRecord": "",
        "pronPrefer": {
            "type": "usa_1",
            "speaker": "male",
            "speed": "standard"
        },
        "ServerRecord": "",
        "ServerUIGS": {
            "version": "new",
            "type": "all",
            "stype": "success",
            "terminal": "web",
            "fr": "default",
            "direction": "etoz",
            "from": "en",
            "to": "zh-CHS",
            "len": 10,
            "qtype": "text",
            "qctype": "qc_1",
            "dict_cover": 1,
            "detail": 1,
            "wordCardCover": 1,
            "wordCardEn": 1,
            "wordCardCh": 0,
            "wordCardMinor": 0,
            "wordCardNetmean": 0,
            "wordDeform": 1,
            "keyword": 0,
            "bilingual": 1,
            "simple": 0,
            "levelList": 1,
            "synonym": 1,
            "antonym": 1,
            "conjugate": 1,
            "rootaffix": 1,
            "baike_sogou": 0,
            "baike_wiki": 0,
            "wordDifference": 1,
            "word_phrase": 1,
            "secondQuery": 0,
            "dict_oxford": 0,
            "dict_newcentury": 0,
            "zhongkaotab": 1,
            "gaokaotab": 1,
            "CET4tab": 1,
            "CET6tab": 1,
            "kaoyantab": 1,
            "network_tab": 0,
            "yinying_tab": 1,
            "tuozhan_tab": 0,
            "one_pic": 0,
            "more_pic": 0,
            "no_pic": 0,
            "uuid": "c019a490-886d-45aa-a912-ea53e13985fc",
            "from_type": 0,
            "t_trans_ssr": 143
        },
        "ServerModelUIGS": {
            "terminal": "web",
            "type": "trans_model",
            "pbtype": "pv",
            "model_general": 1,
            "model_medical": 1,
            "model_finance": 1
        },
        "ServerSgtkn": "65BBB70615C8A60F05032CC6446FC33D05F60C6367559F86",
        "suggShow": false,
        "suggestion": "",
        "suggDirection": "",
        "usualTop": "",
        "baseDict": "",
        "wordCardClick": false,
        "isFrInput": false,
        "kanaTips": {
            "show": false,
            "left": "",
            "top": "",
            "type": "",
            "arrowLeft": ""
        },
        "currSentenceIndex": -1,
        "prefixStrObj": {
            "prefixStr": "",
            "oriPrefixStr": ""
        },
        "selectTransBox": {
            "show": false,
            "right": 0,
            "top": 0,
            "paraphraseInfo": {
                "word": "",
                "from": "",
                "to": "",
                "area": ""
            }
        },
        "sentenceLoading": false,
        "newSentenceInfo": {
            "sentence": "",
            "candidateIndex": 0
        },
        "moreTipInfo": {
            "opacity": 0,
            "zIndex": -1
        },
        "paraphraseShowInfo": {
            "card": 0,
            "query": "",
            "card_dict": 0
        },
        "selectType": "",
        "wordPos": 0,
        "candidateWord": "",
        "syntaxVisible": false,
        "syntaxStatus": 0
    },
    "language": {
        "from": "auto",
        "to": "zh-CHS",
        "detect": "en",
        "model": "general",
        "detectShow": false,
        "langMap": {
            "current": ""
        },
        "zh2en": false,
        "fromItemList": [
            {
                "lang": "auto",
                "text": "自动检测",
                "play": false
            },
            {
                "lang": "en",
                "text": "英语",
                "play": true
            },
            {
                "lang": "zh-CHS",
                "text": "中文",
                "play": true
            },
            {
                "lang": "ja",
                "text": "日语",
                "play": true
            },
            {
                "lang": "ko",
                "text": "韩语",
                "play": true,
                "abbr": "韩"
            },
            {
                "lang": "tr",
                "text": "土耳其语",
                "play": false,
                "abbr": "土"
            },
            {
                "lang": "fr",
                "text": "法语",
                "play": true,
                "abbr": "法"
            }
        ],
        "toItemList": [
            {
                "lang": "zh-CHS",
                "text": "中文",
                "play": true
            },
            {
                "lang": "en",
                "text": "英语",
                "play": true
            },
            {
                "lang": "ja",
                "text": "日语",
                "play": true
            },
            {
                "lang": "ko",
                "text": "韩语",
                "play": true,
                "abbr": "韩"
            },
            {
                "lang": "vi",
                "text": "越南语",
                "play": true,
                "abbr": "越"
            },
            {
                "lang": "th",
                "text": "泰语",
                "play": true,
                "abbr": "泰"
            }
        ]
    },
    "voice": {
        "from": {
            "lang": "en",
            "type": "from",
            "show": true,
            "play": true,
            "src": "/openapi/external/getWebTTS?S-Param=%7B%22text%22%3A%22efficiency%22%2C%22spokenDialect%22%3A%22en%22%2C%22rate%22%3A%220.8%22%7D",
            "list": [
                {
                    "type": "uk_0",
                    "play": true,
                    "show": true,
                    "active": false,
                    "phonetic": "ɪˈfɪʃnsi",
                    "abbr": "英",
                    "src": "http://dlweb.sogoucdn.com/phonetic/sogouvoices/570_efficiency_uk.mp3"
                },
                {
                    "type": "usa_1",
                    "play": true,
                    "show": true,
                    "active": false,
                    "phonetic": "ɪˈfɪʃnsi",
                    "abbr": "美",
                    "src": "http://dlweb.sogoucdn.com/phonetic/sogouvoices/570_efficiency_usa.mp3"
                }
            ],
            "stype": "phonetic",
            "phoneticShow": [
                {
                    "text": "ɪˈfɪʃnsi",
                    "type": "uk",
                    "filename": "http://dlweb.sogoucdn.com/phonetic/sogouvoices/570_efficiency_uk.mp3"
                }
            ]
        },
        "to": {
            "lang": "zh",
            "type": "to",
            "show": true,
            "play": true,
            "src": "/openapi/external/getWebTTS?S-Param=%7B%22text%22%3A%22%E6%95%88%E7%8E%87%22%2C%22spokenDialect%22%3A%22zh-CHS%22%2C%22rate%22%3A%220.8%22%7D",
            "stype": "normal"
        }
    }
}