{
    "word": "forgive",
    "id": 2862,
    "cur_book_name": "oxford3000",
    "default_phonetic": null,
    "us_phonetic": "fərˈɡɪv",
    "uk_phonetic": "fəˈɡɪv",
    "default_audio_url_dict": {},
    "us_audio_url_dict": {
        "bing": "https://dictionary.blob.core.chinacloudapi.cn/media/audio/tom/c4/34/C434D0CFAB7D16E0EB8802F8CBB051DF.mp3",
        "sogou": "http://dlweb.sogoucdn.com/phonetic/sogouvoices/6997_forgive_usa.mp3"
    },
    "uk_audio_url_dict": {
        "bing": "https://dictionary.blob.core.chinacloudapi.cn/media/audio/george/c4/34/C434D0CFAB7D16E0EB8802F8CBB051DF.mp3",
        "sogou": "http://dlweb.sogoucdn.com/phonetic/sogouvoices/6997_forgive_uk.mp3"
    },
    "ai_audio_url_dict": {},
    "default_audio_path_dict": {},
    "us_audio_path_dict": {
        "oxford5000": "sources\\word-audio-libs\\oxford5000\\us\\f\\forgive.mp3",
        "韦氏142000": "sources\\word-audio-libs\\韦氏142000\\us\\f\\forgive.wav"
    },
    "uk_audio_path_dict": {
        "oxford5000": "sources\\word-audio-libs\\oxford5000\\uk\\f\\forgive.mp3"
    },
    "ai_audio_path_dict": {},
    "meaning_str": {
        "bing": "v. 原谅；宽恕；请原谅；对不起\n网络. 饶恕；免除；赦免"
    },
    "meaning_dict": {
        "bing": {
            "v.": "原谅；宽恕；请原谅；对不起",
            "网络.": "饶恕；免除；赦免"
        },
        "sogou": {
            "v.": "原谅；宽恕；饶恕；免除（债务）；赦免；容忍；不追究；停止怀恨；放过；免去（责任或义务）；请原谅；对不起"
        }
    },
    "w_plural": null,
    "w_third": null,
    "w_ing": null,
    "w_done": null,
    "w_past": null,
    "sentence_num": 3,
    "sentence_dict": {
        "bing": {
            "1": {
                "en": "If that's your way of saying no, then I'm glad to hear it. Cause Blair will never forgive you for what you did to her.",
                "cn": "如果你是想否认我也不介意因为Blair永远不会原谅你对她做的事"
            },
            "2": {
                "en": "One night, he dreamt that God appeared to him. Tearfully, he begged God to forgive him for his foolishness.",
                "cn": "一天晚上，陶工又梦见了上帝，他眼泪汪汪地祈求上帝原谅他的愚蠢无知。"
            },
            "3": {
                "en": "You forgive him for the happy days before when you quarrel with him every time . he's good in the memory , well , sort of.",
                "cn": "每一次吵架之后，都用从前那段快乐的日子来原谅他。在回忆里，他是好的，那就算了吧。"
            }
        },
        "sogou": {
            "0": {
                "en": "I think we can <em>forgive</em> him.",
                "cn": "我觉得我们可以原谅他。"
            },
            "1": {
                "en": "Do you <em>forgive</em> me? Do you love me?",
                "cn": "你原谅我吗？你爱我吗？"
            },
            "2": {
                "en": "<em>Forgive</em> me. I was too blind to see.",
                "cn": "原谅我我贪欲迷心没能发现。"
            },
            "3": {
                "en": "You'll <em>forgive</em> them for being a little uptight.",
                "cn": "你得原谅他们可能有点紧张过度。"
            },
            "4": {
                "en": "Oh! Mother Barnabas, <em>forgive</em> me. Get over there.",
                "cn": "芭芭拉修女，请您原谅！别挡路。"
            },
            "5": {
                "en": "<em>Forgive</em> me for using East and West kind of loosely.",
                "cn": "原谅我很不严格地使用东方和西方。"
            },
            "6": {
                "en": "<em>Forgive</em> me, Lawrence. I don't know what came over me.",
                "cn": "原谅我，劳伦斯，我不知道怎么了？"
            },
            "7": {
                "en": "If anything happens to that kid, I'll never <em>forgive</em> myself.",
                "cn": "他要是有个什么三长两短的，我坚决不会原谅我自己。"
            },
            "8": {
                "en": "Please, John, <em>forgive</em> me, for all the hurt that I caused you.",
                "cn": "求你了，约翰，原谅我，原谅我带给你的所有伤害。"
            },
            "9": {
                "en": "<em>Forgive</em> me, madam, for taking up so much of your time.",
                "cn": "原谅我，小姐，耽搁了你这么多的时间。"
            },
            "10": {
                "en": "You don't have to <em>forgive</em> him. But we shouldn't forget him.",
                "cn": "你不用原谅他，但我们不能忘记他。"
            },
            "11": {
                "en": "<em>Forgive</em> me, but are you acquainted with him, with Mr Darcy?",
                "cn": "请原谅我的冒昧 你和达西先生很熟吗？"
            },
            "12": {
                "en": "You don't understand. I lied to him. He'll never <em>forgive</em> me.",
                "cn": "你不懂，我骗了他，他再也不会原谅我了。"
            },
            "13": {
                "en": "I'm so sorry. If it's not too late, please <em>forgive</em> me.",
                "cn": "我非常抱歉，如果还不太晚的话，请你原谅我吧。"
            },
            "14": {
                "en": "I can't, I can't do it, John. I don't know how. <em>Forgive</em> me.",
                "cn": "我做不到，约翰，我做不到，我不会这个，请原谅我。"
            },
            "15": {
                "en": "Now, look, I'm not trying to ask you to <em>forgive</em> him being in that photograph.",
                "cn": "我不会试着让你们原谅他出现在那张照片中。"
            },
            "16": {
                "en": "I would never <em>forgive</em> myself if I put too much on your plate too soon.",
                "cn": "如果我操之过急让你压力太大，我绝不会原谅自己。"
            },
            "17": {
                "en": "Amy just burned Jo's manuscript. I don't see how he could ever <em>forgive</em> her.",
                "cn": "爱美刚烧了乔的稿子，我看他永远不会原谅她。"
            },
            "18": {
                "en": "<em>Forgive</em> me for eavesdropping, but as I see it, there's a simple solution.",
                "cn": "原谅我偷听了，但在我看来，有一个简单的解决办法。"
            },
            "19": {
                "en": "Hope you'll <em>forgive</em> me. For? I was meeting Vice President Francis Underwood. I thought he deserved a good story.",
                "cn": "希望你能原谅我。原谅什么？我那天见到了副总统弗兰西斯·安德伍德，我觉得应该给他讲个精彩的传说。"
            }
        }
    },
    "sentence_audio_url_dict": {
        "bing": {
            "1": "https://dictionary.blob.core.chinacloudapi.cn/media/audio/tom/0d/06/0D0654A62174620C3F1A784BFAD159F3.mp3",
            "2": "https://dictionary.blob.core.chinacloudapi.cn/media/audio/tom/94/34/943461E1DA9D8E11460968EED8CE0B55.mp3",
            "3": "https://dictionary.blob.core.chinacloudapi.cn/media/audio/tom/18/56/185669F9019683EDEB20DB764BB3E91E.mp3"
        },
        "sogou": {
            "0": "http://pic03.sogoucdn.com/s3/a/201051/dec6aaae9ce2b6c5fe20867816309496_5904.mp3",
            "1": "http://pic04.sogoucdn.com/s3/a/201051/5c392caa4af2dd2970dfebb696450dd5_53383.mp3",
            "2": "http://pic04.sogoucdn.com/s3/a/201051/6ce1c623be539e7eb52163ef1c7a913d_53109.mp3",
            "3": "http://pic03.sogoucdn.com/s3/a/201051/a91e5c8029dd6d2c90e0d9b96176c94b_64090.mp3",
            "4": "http://pic01.sogoucdn.com/s3/a/201051/c5c6ab1cfeee745b3af565d20be0bca7_35364.mp3",
            "5": "http://pic01.sogoucdn.com/s3/a/201051/c92a5682ce0d1110befd30e0bfc9f318_3695.mp3",
            "6": "http://pic03.sogoucdn.com/s3/a/201051/dd8e0d510602de251bec9f8cd8c9a53b_51749.mp3",
            "7": "http://pic04.sogoucdn.com/s3/a/201051/5a5c694d0e52d7126ea538586ffa654d_68611.mp3",
            "8": "http://pic03.sogoucdn.com/s3/a/201051/8eae15b46bd4035a9ba0061a9d62bbb2_29496.mp3",
            "9": "http://pic01.sogoucdn.com/s3/a/201051/77f34e18e3889796e035c93d10b2f29f_2291.mp3",
            "10": "http://pic03.sogoucdn.com/s3/a/201051/362537775f1a0619b85955523fe542ad_48305.mp3",
            "11": "http://pic03.sogoucdn.com/s3/a/201051/60a913c81811fe2d0ac5041545aeda66_66718.mp3",
            "12": "http://pic04.sogoucdn.com/s3/a/201051/4d094dc61bb583abc3eef74a6d709fcd_47146.mp3",
            "13": "http://pic04.sogoucdn.com/s3/a/201051/99ddf7dfdab885914b6a4d69a4a3e309_46695.mp3",
            "14": "http://pic02.sogoucdn.com/s3/a/201051/7d14a420e30b4f2d86f6e17f805a378a_43972.mp3",
            "15": "http://pic01.sogoucdn.com/s3/a/201051/8ddae96cdcb12ddf65720a3433ea4713_73394.mp3",
            "16": "http://pic02.sogoucdn.com/s3/a/201051/a2c85b023f661973872079e94ed392d3_30781.mp3",
            "17": "http://pic03.sogoucdn.com/s3/a/201051/f58ffca331467e0c7290ed69f603a042_36450.mp3",
            "18": "http://pic03.sogoucdn.com/s3/a/201051/bd625b9b2eedcf9b456a651a2cf65d73_29020.mp3",
            "19": "http://pic01.sogoucdn.com/s3/a/201051/aa3ee8a476aa02c1599e8ef9d41efa70_39004.mp3"
        }
    },
    "sentence_audio_path_dict": {},
    "picture_num": 0,
    "picture_url_dict": {
        "bing": []
    },
    "picture_path_dict": {},
    "level": null,
    "oxford_level": null
}