{
    "word": "decrease",
    "id": 2753,
    "cur_book_name": "oxford3000",
    "default_phonetic": null,
    "us_phonetic": "dɪˈkriːs , ˈdiːkriːs",
    "uk_phonetic": "dɪˈkriːs , ˈdiːkriːs",
    "default_audio_url_dict": {},
    "us_audio_url_dict": {
        "bing": "https://dictionary.blob.core.chinacloudapi.cn/media/audio/tom/a6/9c/A69C1108ADC58AE9410ADE5E7EC875FD.mp3",
        "sogou": "http://dlweb.sogoucdn.com/phonetic/sogouvoices/2045_decrease_usa.mp3"
    },
    "uk_audio_url_dict": {
        "bing": "https://dictionary.blob.core.chinacloudapi.cn/media/audio/george/a6/9c/A69C1108ADC58AE9410ADE5E7EC875FD.mp3",
        "sogou": "http://dlweb.sogoucdn.com/phonetic/sogouvoices/2045_decrease_uk.mp3"
    },
    "ai_audio_url_dict": {},
    "default_audio_path_dict": {},
    "us_audio_path_dict": {
        "oxford5000": "sources\\word-audio-libs\\oxford5000\\us\\d\\decrease.mp3",
        "韦氏142000": "sources\\word-audio-libs\\韦氏142000\\us\\d\\decrease.wav"
    },
    "uk_audio_path_dict": {
        "oxford5000": "sources\\word-audio-libs\\oxford5000\\uk\\d\\decrease.mp3"
    },
    "ai_audio_path_dict": {},
    "meaning_str": {
        "bing": "v. 降低；减少；缩小；减弱\nn. 减少；减小量；所减少的总量；减缩位置\n网络. 下降；减少量；减少之量"
    },
    "meaning_dict": {
        "bing": {
            "v.": "降低；减少；缩小；减弱",
            "n.": "减少；减小量；所减少的总量；减缩位置",
            "网络.": "下降；减少量；减少之量"
        },
        "sogou": {
            "v.": "降低；缩减；（使大小、数量等）减小；降低；缩小；减轻；减缓；下降；减退；削减；减弱",
            "n.": "减少；下降；降低；减小；缩减；衰减；减少量；减小过程；降低幅度"
        }
    },
    "w_plural": null,
    "w_third": null,
    "w_ing": null,
    "w_done": null,
    "w_past": null,
    "sentence_num": 3,
    "sentence_dict": {
        "bing": {
            "1": {
                "en": "Noss's efforts seem to be paying off. He says he has seen ample satisfaction rise and turnover decrease by a noticeable percentage.",
                "cn": "诺斯的努力似乎已经渐收成效，他表示员工对公司的满意度大幅提升，员工跳槽的频率也明显降低。"
            },
            "2": {
                "en": "Bone microdamage is often accompanied with the decrease of bone strength and the increase of bone fragility.",
                "cn": "显微损伤往往伴有骨强度的降低和骨脆性的增加，裂纹的长度及其位置是影响骨力学性能的决定因素。"
            },
            "3": {
                "en": "But to tell you the truth, the room is so large that I can share it with someone else, and that will decrease the total amount of the rent.",
                "cn": "是的，但实话告诉你，房间很大，所以我可以和其他人合租，这样就能减少租金的数额。"
            }
        },
        "sogou": {
            "0": {
                "en": "But deflation would make people want to hold onto their money, and a <em>decrease</em> in consumer spending would reduce business profits, leading to more unemployment and a further <em>decrease</em> in spending, causing the economy to keep shrinking.",
                "cn": "然而，通货紧缩会让人不愿花钱，减少消费支出，造成商业利润下跌，失业率升高，进一步重挫消费，导致经济不断紧缩。"
            },
            "1": {
                "en": "But deflation would make people want to hold onto their money, and a <em>decrease</em> in consumer spending would reduce business profits, leading to more unemployment and a further <em>decrease</em> in spending, causing the economy to keep shrinking.",
                "cn": "然而，通货紧缩会让人不愿花钱，减少消费支出，造成商业利润下跌，失业率升高，进一步重挫消费，导致经济不断紧缩。"
            },
            "2": {
                "en": "PTSD patients generally have a <em>decrease</em> in brain communication between the amygdala and the hippocampus.",
                "cn": "普遍来说，创伤后压力症候群患者脑中杏仁核和海马回的连结较差。"
            }
        }
    },
    "sentence_audio_url_dict": {
        "bing": {
            "1": "https://dictionary.blob.core.chinacloudapi.cn/media/audio/tom/9e/9a/9E9A58BE8B0D73B444A784455F5F5222.mp3",
            "2": "https://dictionary.blob.core.chinacloudapi.cn/media/audio/tom/96/67/96674FC2DE53B2888296AC114D57A32F.mp3",
            "3": "https://dictionary.blob.core.chinacloudapi.cn/media/audio/tom/bd/33/BD33F96830F2444623FD8E31E8D2F083.mp3"
        },
        "sogou": {
            "0": "http://pic03.sogoucdn.com/s3/a/201051/540872d63cec5d5ed8791144aa182d9d_35296.mp3",
            "1": "http://pic03.sogoucdn.com/s3/a/201051/61df94c63a7ca16711eecb461094626f_22166.mp3",
            "2": "http://pic03.sogoucdn.com/s3/a/201051/da018780052a48c74ff869b238527a40_25482.mp3"
        }
    },
    "sentence_audio_path_dict": {},
    "picture_num": 0,
    "picture_url_dict": {
        "bing": []
    },
    "picture_path_dict": {},
    "level": null,
    "oxford_level": null
}